plone.resourceeditor-4.0.2-py3.13-nspkg.pth
plone/resourceeditor/__init__.py
plone/resourceeditor/browser.py
plone/resourceeditor/configure.zcml
plone/resourceeditor/editor.pt
plone/resourceeditor/mime.types
plone/resourceeditor/preview.pt
plone/resourceeditor/testing.py
plone/resourceeditor/tests/__init__.py
plone/resourceeditor/tests/test_file_manager.py
plone/resourceeditor/tests/test_file_manager_action.py
plone_resourceeditor-4.0.2.dist-info/METADATA
plone_resourceeditor-4.0.2.dist-info/WHEEL
plone_resourceeditor-4.0.2.dist-info/namespace_packages.txt
plone_resourceeditor-4.0.2.dist-info/top_level.txt
plone_resourceeditor-4.0.2.dist-info/RECORD
